ldb/__init__.py
ldb/add.py
ldb/app_info.py
ldb/cli.py
ldb/cli_utils.py
ldb/collections.py
ldb/commit.py
ldb/config.py
ldb/core.py
ldb/data_formats.py
ldb/data_object_tag.py
ldb/dataset.py
ldb/diff.py
ldb/ds.py
ldb/env.py
ldb/evaluate.py
ldb/exceptions.py
ldb/func_utils.py
ldb/get.py
ldb/import_utils.py
ldb/instantiate.py
ldb/iter_utils.py
ldb/ls.py
ldb/main.py
ldb/op_type.py
ldb/params.py
ldb/path.py
ldb/pipe.py
ldb/progress.py
ldb/pull.py
ldb/stage.py
ldb/status.py
ldb/storage.py
ldb/string_utils.py
ldb/transform.py
ldb/typing.py
ldb/utils.py
ldb/version.py
ldb/warnings.py
ldb/workspace.py
ldb/command/__init__.py
ldb/command/add.py
ldb/command/add_storage.py
ldb/command/commit.py
ldb/command/completion.py
ldb/command/delete.py
ldb/command/diff.py
ldb/command/ds.py
ldb/command/evaluate.py
ldb/command/get.py
ldb/command/index.py
ldb/command/init.py
ldb/command/instantiate.py
ldb/command/ls.py
ldb/command/pull.py
ldb/command/stage.py
ldb/command/status.py
ldb/command/sync.py
ldb/command/tag.py
ldb/command/transform.py
ldb/command/unindex.py
ldb/fs/__init__.py
ldb/fs/path.py
ldb/fs/utils.py
ldb/index/__init__.py
ldb/index/annotation_only.py
ldb/index/base.py
ldb/index/inferred.py
ldb/index/label_studio.py
ldb/index/utils.py
ldb/jmespath/__init__.py
ldb/jmespath/exceptions.py
ldb/jmespath/parser.py
ldb/plugins/__init__.py
ldb/plugins/clip_image.py
ldb/plugins/clip_text.py
ldb/plugins/clip_utils.py
ldb/plugins/registry.py
ldb/plugins/resnet_image.py
ldb/plugins/resnet_utils.py
ldb/plugins/utils.py
ldb/query/__init__.py
ldb/query/functions.py
ldb/query/search.py
ldb/query/user_functions.py
ldb/query/utils.py
ldb_alpha-0.7.0.dist-info/LICENSE
ldb_alpha-0.7.0.dist-info/METADATA
ldb_alpha-0.7.0.dist-info/WHEEL
ldb_alpha-0.7.0.dist-info/entry_points.txt
ldb_alpha-0.7.0.dist-info/top_level.txt
ldb_alpha-0.7.0.dist-info/RECORD
