Metadata-Version: 2.1
Name: ldb-alpha
Version: 0.7.0
Summary: A command line tool for data-centric science and machine learning projects
Home-page: https://github.com/iterative/ldb
Author: Jon Burdo
Author-email: jon@jonburdo.com
Maintainer: Iterative
Maintainer-email: support@iterative.ai
License: Apache-2.0
Classifier: Development Status :: 3 - Alpha
Requires-Python: >=3.7
License-File: LICENSE
Requires-Dist: appdirs (>=1.4.3)
Requires-Dist: fsspec (>=2021.10.1)
Requires-Dist: funcy (>=1.17)
Requires-Dist: jmespath (>=0.10.0)
Requires-Dist: rich (>=12.0.1)
Requires-Dist: shtab (<2,>=1.3.4)
Requires-Dist: tomlkit (<1.0.0,>=0.9.1)
Requires-Dist: typing-extensions (>=4.0.0)
Provides-Extra: clip-plugin
Requires-Dist: clip-anytorch (>=2.3.0) ; extra == 'clip-plugin'
Provides-Extra: dev
Requires-Dist: clip-anytorch (>=2.3.0) ; extra == 'dev'
Requires-Dist: torch (>=1.10.1) ; extra == 'dev'
Requires-Dist: torchvision (>=0.11.2) ; extra == 'dev'
Requires-Dist: s3fs (>=2021.11.1) ; extra == 'dev'
Requires-Dist: pytest (>=6.2.5) ; extra == 'dev'
Requires-Dist: pytest-xdist (>=2.5.0) ; extra == 'dev'
Requires-Dist: mypy (>=0.910) ; extra == 'dev'
Requires-Dist: pre-commit (>=2.9.2) ; extra == 'dev'
Requires-Dist: pyannotate (>=1.2.0) ; extra == 'dev'
Requires-Dist: pylint (<2.15.0,>=2.14.5) ; extra == 'dev'
Requires-Dist: pylint-pytest (>=1.1.2) ; extra == 'dev'
Requires-Dist: types-all (>=1.0.0) ; extra == 'dev'
Requires-Dist: types-appdirs (>=1.4.1) ; extra == 'dev'
Requires-Dist: types-jmespath (>=0.10.0) ; extra == 'dev'
Requires-Dist: types-setuptools (>=57.4.2) ; extra == 'dev'
Requires-Dist: autoflake (>=1.4) ; extra == 'dev'
Provides-Extra: lint
Requires-Dist: clip-anytorch (>=2.3.0) ; extra == 'lint'
Requires-Dist: torch (>=1.10.1) ; extra == 'lint'
Requires-Dist: torchvision (>=0.11.2) ; extra == 'lint'
Requires-Dist: s3fs (>=2021.11.1) ; extra == 'lint'
Requires-Dist: pytest (>=6.2.5) ; extra == 'lint'
Requires-Dist: pytest-xdist (>=2.5.0) ; extra == 'lint'
Requires-Dist: mypy (>=0.910) ; extra == 'lint'
Requires-Dist: pre-commit (>=2.9.2) ; extra == 'lint'
Requires-Dist: pyannotate (>=1.2.0) ; extra == 'lint'
Requires-Dist: pylint (<2.15.0,>=2.14.5) ; extra == 'lint'
Requires-Dist: pylint-pytest (>=1.1.2) ; extra == 'lint'
Requires-Dist: types-all (>=1.0.0) ; extra == 'lint'
Requires-Dist: types-appdirs (>=1.4.1) ; extra == 'lint'
Requires-Dist: types-jmespath (>=0.10.0) ; extra == 'lint'
Requires-Dist: types-setuptools (>=57.4.2) ; extra == 'lint'
Provides-Extra: resnet-plugin
Requires-Dist: torch (>=1.10.1) ; extra == 'resnet-plugin'
Requires-Dist: torchvision (>=0.11.2) ; extra == 'resnet-plugin'
Provides-Extra: s3
Requires-Dist: s3fs (>=2021.11.1) ; extra == 's3'
Provides-Extra: test
Requires-Dist: clip-anytorch (>=2.3.0) ; extra == 'test'
Requires-Dist: torch (>=1.10.1) ; extra == 'test'
Requires-Dist: torchvision (>=0.11.2) ; extra == 'test'
Requires-Dist: s3fs (>=2021.11.1) ; extra == 'test'
Requires-Dist: pytest (>=6.2.5) ; extra == 'test'
Requires-Dist: pytest-xdist (>=2.5.0) ; extra == 'test'
Provides-Extra: test-setup
Requires-Dist: dvc[s3] (>=2.8.2) ; extra == 'test-setup'
